{
  "name": "15y_v3_nobeccs",
  "data": [
    {
      "seriesName": "DMD_TRA-F-LTRUCK-BEV",
      "seriesValues": [
        [
          2019,
          2.48085
        ],
        [
          2020,
          0.727
        ],
        [
          2021,
          4.14975946899599
        ],
        [
          2022,
          6.31063578802492
        ],
        [
          2023,
          9.50976220846632
        ],
        [
          2024,
          14.3739418008897
        ],
        [
          2025,
          21.6926309572565
        ],
        [
          2026,
          18.2702946920298
        ],
        [
          2027,
          17.9693248868318
        ],
        [
          2028,
          18.3158475574341
        ],
        [
          2029,
          21.0717782388553
        ],
        [
          2030,
          25.6283317194432
        ],
        [
          2031,
          34.2983400001295
        ],
        [
          2032,
          43.0704285400567
        ],
        [
          2033,
          49.3597016690254
        ],
        [
          2034,
          52.5784255897431
        ],
        [
          2035,
          47.7273922880826
        ],
        [
          2036,
          45.6057654291201
        ],
        [
          2037,
          29.3976015717866
        ],
        [
          2038,
          29.8542646039768
        ],
        [
          2039,
          31.1427891879858
        ],
        [
          2040,
          37.1987185084144
        ],
        [
          2041,
          39.2994941707048
        ],
        [
          2042,
          45.2520195683881
        ],
        [
          2043,
          40.3051578786077
        ],
        [
          2044,
          43.3740126067348
        ],
        [
          2045,
          46.5871327876755
        ],
        [
          2046,
          46.112701373685
        ],
        [
          2047,
          45.8595193160636
        ],
        [
          2048,
          45.5801774784652
        ],
        [
          2049,
          45.7176081812872
        ],
        [
          2050,
          46.8625849922703
        ],
        [
          2051,
          49.4988991544686
        ],
        [
          2052,
          53.3289022308057
        ],
        [
          2055,
          174.587083966033
        ],
        [
          2060,
          299.236171924257
        ],
        [
          2065,
          339.242476504283
        ],
        [
          2070,
          368.087053769809
        ]
      ]
    },
    {
      "seriesName": "DMD_TRA-F-LTRUCK-ICE",
      "seriesValues": [
        [
          2020,
          20.928
        ],
        [
          2021,
          18.4625975533199
        ],
        [
          2023,
          16.8943239000627
        ],
        [
          2024,
          11.9378769657049
        ],
        [
          2025,
          1.60466938281242
        ]
      ]
    }
  ]
}