{
  "name": "15y_v3",
  "data": [
    {
      "seriesName": "TRABDL",
      "seriesValues": [
        [
          2018,
          0.316426720789586
        ],
        [
          2019,
          0.2228874454672229
        ],
        [
          2020,
          0.2726003359662325
        ],
        [
          2021,
          0.8388824727272709
        ],
        [
          2022,
          1.8760857371087938
        ],
        [
          2023,
          1.6750094040975896
        ],
        [
          2024,
          1.1292088071805928
        ],
        [
          2025,
          0.848377830017637
        ],
        [
          2026,
          0.9041463775247495
        ],
        [
          2027,
          0.7051188780270314
        ],
        [
          2028,
          0.4569555375537223
        ],
        [
          2029,
          0.479356352352487
        ]
      ]
    },
    {
      "seriesName": "TRADST",
      "seriesValues": [
        [
          2018,
          7.40814607173318
        ],
        [
          2019,
          10.659318031711196
        ],
        [
          2020,
          9.579433923988685
        ],
        [
          2021,
          7.549942254545455
        ],
        [
          2022,
          5.940938167511178
        ],
        [
          2023,
          5.13696856992838
        ],
        [
          2024,
          4.509328080700541
        ],
        [
          2025,
          3.977922354008868
        ],
        [
          2026,
          2.7466960950057238
        ],
        [
          2027,
          1.9246696739428661
        ],
        [
          2028,
          1.2674166141057217
        ],
        [
          2029,
          0.3575624675307029
        ]
      ]
    },
    {
      "seriesName": "TRAELC",
      "seriesValues": [
        [
          2021,
          0.4415170909090896
        ],
        [
          2024,
          0.1765662606776246
        ],
        [
          2026,
          0.1946289644196724
        ],
        [
          2027,
          0.24273228045069858
        ],
        [
          2028,
          0.1829816810678273
        ],
        [
          2029,
          0.11295858685350041
        ]
      ]
    }
  ]
}