{
  "name": "15y_v4",
  "data": [
    {
      "seriesName": "PWR-COA",
      "seriesValues": [
        [
          2018,
          1.253
        ],
        [
          2019,
          1.253
        ],
        [
          2020,
          1.253
        ],
        [
          2021,
          1.253
        ],
        [
          2022,
          1.253
        ],
        [
          2023,
          1.253
        ],
        [
          2024,
          1.253
        ],
        [
          2025,
          0.398
        ],
        [
          2026,
          0.398
        ],
        [
          2027,
          0.398
        ],
        [
          2028,
          0.398
        ],
        [
          2029,
          0.398
        ],
        [
          2030,
          0.398
        ],
        [
          2031,
          0.199
        ]
      ]
    },
    {
      "seriesName": "PWR-GAS",
      "seriesValues": [
        [
          2018,
          4.933
        ],
        [
          2019,
          4.933
        ],
        [
          2020,
          4.933
        ],
        [
          2021,
          5.919043461128734
        ],
        [
          2022,
          5.919043461128734
        ],
        [
          2023,
          5.829043461128734
        ],
        [
          2024,
          5.649043461128734
        ],
        [
          2025,
          5.649043461128734
        ],
        [
          2026,
          5.649043461128734
        ],
        [
          2027,
          5.649043461128734
        ],
        [
          2028,
          5.649043461128734
        ],
        [
          2029,
          5.649043461128734
        ],
        [
          2030,
          5.137043461128734
        ],
        [
          2031,
          5.137043461128734
        ],
        [
          2032,
          4.390043461128734
        ],
        [
          2033,
          4.390043461128734
        ],
        [
          2034,
          4.390043461128734
        ],
        [
          2035,
          4.390043461128734
        ],
        [
          2036,
          3.986043461128734
        ],
        [
          2037,
          3.578043461128734
        ],
        [
          2038,
          2.9830434611287338
        ],
        [
          2039,
          2.9830434611287338
        ],
        [
          2040,
          1.533043461128734
        ],
        [
          2041,
          1.533043461128734
        ],
        [
          2042,
          1.429043461128734
        ],
        [
          2043,
          1.429043461128734
        ],
        [
          2044,
          1.429043461128734
        ],
        [
          2045,
          1.417043461128734
        ],
        [
          2046,
          1.417043461128734
        ],
        [
          2047,
          1.417043461128734
        ],
        [
          2048,
          1.417043461128734
        ],
        [
          2049,
          0.986043461128734
        ],
        [
          2050,
          0.986043461128734
        ]
      ]
    },
    {
      "seriesName": "PWR-HYD",
      "seriesValues": [
        [
          2018,
          0.216
        ],
        [
          2019,
          0.216
        ],
        [
          2020,
          0.216
        ],
        [
          2021,
          0.5522445942354619
        ],
        [
          2022,
          0.554177381556377
        ],
        [
          2023,
          0.556110168877292
        ],
        [
          2024,
          0.558042956198207
        ],
        [
          2025,
          0.559975743519123
        ],
        [
          2026,
          0.561908530840038
        ],
        [
          2027,
          0.563841318160953
        ],
        [
          2028,
          0.5657741054818679
        ],
        [
          2029,
          0.567706892802783
        ],
        [
          2030,
          0.569639680123698
        ],
        [
          2031,
          0.571572467444614
        ],
        [
          2032,
          0.573505254765529
        ],
        [
          2033,
          0.575438042086444
        ],
        [
          2034,
          0.577370829407359
        ],
        [
          2035,
          0.5793036167282739
        ],
        [
          2036,
          0.58123640404919
        ],
        [
          2037,
          0.5831691913701049
        ],
        [
          2038,
          0.58510197869102
        ],
        [
          2039,
          0.587034766011935
        ],
        [
          2040,
          0.58896755333285
        ],
        [
          2041,
          0.590900340653766
        ],
        [
          2042,
          0.592833127974681
        ],
        [
          2043,
          0.594765915295596
        ],
        [
          2044,
          0.631244221877742
        ],
        [
          2045,
          0.6312797971351
        ],
        [
          2046,
          0.6312797971351
        ],
        [
          2047,
          0.6312797971351
        ],
        [
          2048,
          0.6312797971351
        ],
        [
          2049,
          0.6312797971351
        ],
        [
          2050,
          0.6312797971351
        ],
        [
          2051,
          0.6312797971351
        ],
        [
          2052,
          0.6312797971351
        ],
        [
          2055,
          0.6312797971351
        ],
        [
          2060,
          0.634522128365016
        ],
        [
          2065,
          0.634522128365016
        ],
        [
          2070,
          0.634522128365016
        ]
      ]
    },
    {
      "seriesName": "PWR-OIL",
      "seriesValues": [
        [
          2018,
          1.229
        ],
        [
          2019,
          1.229
        ],
        [
          2020,
          1.229
        ],
        [
          2021,
          1.229
        ],
        [
          2022,
          1.229
        ],
        [
          2023,
          0.635
        ],
        [
          2024,
          0.635
        ],
        [
          2025,
          0.635
        ],
        [
          2026,
          0.519
        ],
        [
          2027,
          0.519
        ],
        [
          2028,
          0.519
        ],
        [
          2029,
          0.519
        ],
        [
          2030,
          0.519
        ],
        [
          2031,
          0.519
        ],
        [
          2032,
          0.519
        ],
        [
          2033,
          0.41500000000000004
        ],
        [
          2034,
          0.311
        ],
        [
          2035,
          0.311
        ],
        [
          2036,
          0.311
        ],
        [
          2037,
          0.311
        ],
        [
          2038,
          0.311
        ],
        [
          2039,
          0.311
        ],
        [
          2040,
          0.14200000000000002
        ],
        [
          2041,
          0.14200000000000002
        ],
        [
          2042,
          0.14200000000000002
        ],
        [
          2043,
          0.14200000000000002
        ]
      ]
    },
    {
      "seriesName": "PWR-PEA",
      "seriesValues": [
        [
          2018,
          0.351
        ],
        [
          2019,
          0.351
        ],
        [
          2020,
          0.118
        ],
        [
          2021,
          0.118
        ],
        [
          2022,
          0.118
        ]
      ]
    },
    {
      "seriesName": "PWR-WIN-OF",
      "seriesValues": [
        [
          2018,
          0.025
        ],
        [
          2019,
          0.025
        ],
        [
          2020,
          0.0670010551316081
        ],
        [
          2021,
          0.58040126615793
        ],
        [
          2022,
          1.19648151938952
        ],
        [
          2023,
          1.9357778232674199
        ],
        [
          2024,
          2.8229333879208998
        ],
        [
          2025,
          3.88752006550508
        ],
        [
          2026,
          5.1650240786061
        ],
        [
          2027,
          6.264
        ],
        [
          2028,
          6.696
        ],
        [
          2029,
          7.128
        ],
        [
          2030,
          7.56
        ],
        [
          2031,
          8.682
        ],
        [
          2032,
          9.804
        ],
        [
          2033,
          10.926
        ],
        [
          2034,
          12.048
        ],
        [
          2035,
          13.17
        ],
        [
          2036,
          14.292
        ],
        [
          2037,
          15.414
        ],
        [
          2038,
          16.536
        ],
        [
          2039,
          17.658
        ],
        [
          2040,
          18.78
        ],
        [
          2041,
          19.902
        ],
        [
          2042,
          21.024
        ],
        [
          2043,
          22.146
        ],
        [
          2044,
          23.268
        ],
        [
          2045,
          24.39
        ],
        [
          2046,
          25.409307404993
        ],
        [
          2047,
          26.23471191395
        ],
        [
          2048,
          26.7791328035279
        ],
        [
          2049,
          27.2754775996548
        ],
        [
          2050,
          27.6593245829589
        ],
        [
          2051,
          28.3541357249967
        ],
        [
          2052,
          28.6916195367281
        ],
        [
          2055,
          30.0
        ],
        [
          2060,
          30.0
        ],
        [
          2065,
          30.0
        ],
        [
          2070,
          30.0
        ]
      ]
    },
    {
      "seriesName": "PWR-WIN-ON",
      "seriesValues": [
        [
          2018,
          3.469
        ],
        [
          2019,
          3.625
        ],
        [
          2020,
          4.85
        ],
        [
          2021,
          6.32
        ],
        [
          2022,
          6.390000000000001
        ],
        [
          2023,
          6.46
        ],
        [
          2024,
          6.529999999999999
        ],
        [
          2025,
          6.6
        ],
        [
          2026,
          6.68
        ],
        [
          2027,
          6.76
        ],
        [
          2028,
          6.84
        ],
        [
          2029,
          6.92
        ],
        [
          2030,
          7.0
        ],
        [
          2031,
          7.0600000000000005
        ],
        [
          2032,
          7.12
        ],
        [
          2033,
          7.18
        ],
        [
          2034,
          7.24
        ],
        [
          2035,
          7.300000000000001
        ],
        [
          2036,
          7.359999999999999
        ],
        [
          2037,
          7.42
        ],
        [
          2038,
          7.4799999999999995
        ],
        [
          2039,
          7.54
        ],
        [
          2040,
          7.6
        ],
        [
          2041,
          7.66
        ],
        [
          2042,
          7.720000000000001
        ],
        [
          2043,
          7.78
        ],
        [
          2044,
          7.84
        ],
        [
          2045,
          7.9
        ],
        [
          2046,
          7.96
        ],
        [
          2047,
          8.02
        ],
        [
          2048,
          8.08
        ],
        [
          2049,
          8.139999999999999
        ],
        [
          2050,
          8.2
        ],
        [
          2051,
          8.2
        ],
        [
          2052,
          8.2
        ],
        [
          2055,
          8.2
        ],
        [
          2060,
          8.2
        ],
        [
          2065,
          8.2
        ],
        [
          2070,
          8.2
        ]
      ]
    },
    {
      "seriesName": "PWR-SOL",
      "seriesValues": [
        [
          2020,
          0.0587107679222489
        ],
        [
          2021,
          0.570452921506699
        ],
        [
          2022,
          0.867745149890839
        ],
        [
          2023,
          1.13722757465396
        ],
        [
          2024,
          1.55348056037421
        ],
        [
          2025,
          1.74331956263435
        ],
        [
          2026,
          2.23802046988559
        ],
        [
          2027,
          2.69064404938247
        ],
        [
          2028,
          3.00400775432261
        ],
        [
          2029,
          3.25626145540853
        ],
        [
          2030,
          3.25626145540853
        ],
        [
          2031,
          3.25626145540853
        ],
        [
          2032,
          3.49664685697481
        ],
        [
          2033,
          3.61725548070001
        ],
        [
          2034,
          3.68062543608051
        ],
        [
          2035,
          3.68062543608051
        ],
        [
          2036,
          3.82599045815479
        ],
        [
          2037,
          3.90438531034739
        ],
        [
          2038,
          3.95430328091388
        ],
        [
          2039,
          4.02298197712099
        ],
        [
          2040,
          4.04594925484356
        ],
        [
          2041,
          4.09807635713323
        ],
        [
          2042,
          4.14247124943651
        ],
        [
          2043,
          4.16696732749406
        ],
        [
          2044,
          4.18159890475931
        ],
        [
          2045,
          4.30511940414682
        ],
        [
          2046,
          4.4313363365286
        ],
        [
          2047,
          4.57675384183856
        ],
        [
          2048,
          4.72985291316459
        ],
        [
          2049,
          4.83770683371249
        ],
        [
          2050,
          5.02797328793172
        ],
        [
          2051,
          5.09363880879088
        ],
        [
          2052,
          5.11705820067997
        ],
        [
          2055,
          5.20066814359883
        ],
        [
          2060,
          5.28123889463146
        ],
        [
          2065,
          5.40255351612506
        ],
        [
          2070,
          5.39932781847859
        ]
      ]
    },
    {
      "seriesName": "PWR-OCE",
      "seriesValues": [
        [
          2035,
          0.1
        ],
        [
          2036,
          0.22
        ],
        [
          2037,
          0.364
        ],
        [
          2038,
          0.45
        ],
        [
          2039,
          0.475
        ],
        [
          2040,
          0.5
        ],
        [
          2041,
          0.55
        ],
        [
          2042,
          0.6
        ],
        [
          2043,
          0.65
        ],
        [
          2044,
          0.7
        ],
        [
          2045,
          0.7
        ],
        [
          2046,
          0.7
        ],
        [
          2047,
          0.7
        ],
        [
          2048,
          0.7
        ],
        [
          2049,
          0.7
        ],
        [
          2050,
          0.7
        ],
        [
          2051,
          0.7
        ],
        [
          2052,
          0.7
        ],
        [
          2055,
          0.741564325855806
        ],
        [
          2060,
          1.789822935859588
        ],
        [
          2065,
          2.8717564021926503
        ],
        [
          2070,
          4.45352092670508
        ]
      ]
    },
    {
      "seriesName": "PWR-H2",
      "seriesValues": [
        [
          2070,
          0.18138690275815
        ]
      ]
    }
  ]
}